socrates_api/__init__.py
socrates_api/database.py
socrates_api/main.py
socrates_api/models.py
socrates_api/monitoring.py
socrates_api/testing_mode.py
socrates_ai_api-1.3.3.dist-info/METADATA
socrates_ai_api-1.3.3.dist-info/WHEEL
socrates_ai_api-1.3.3.dist-info/entry_points.txt
socrates_ai_api-1.3.3.dist-info/top_level.txt
socrates_ai_api-1.3.3.dist-info/RECORD
