Metadata-Version: 2.4
Name: socrates-ai-api
Version: 1.3.3
Summary: REST API server for Socrates AI with GitHub-ready project generation, export, and publishing capabilities
Author: Socrates AI Contributors
License: MIT
Project-URL: Homepage, https://github.com/Nireus79/Socrates
Project-URL: Repository, https://github.com/Nireus79/Socrates
Project-URL: Bug Tracker, https://github.com/Nireus79/Socrates/issues
Project-URL: Source Code, https://github.com/Nireus79/Socrates/tree/main/socrates-api
Keywords: api,rest,fastapi,socrates,ai,tutoring,github,export,git,ci-cd
Classifier: Development Status :: 5 - Production/Stable
Classifier: Intended Audience :: Developers
Classifier: License :: OSI Approved :: MIT License
Classifier: Programming Language :: Python :: 3
Classifier: Programming Language :: Python :: 3.8
Classifier: Programming Language :: Python :: 3.9
Classifier: Programming Language :: Python :: 3.10
Classifier: Programming Language :: Python :: 3.11
Classifier: Programming Language :: Python :: 3.12
Classifier: Environment :: Web Environment
Classifier: Topic :: Education
Classifier: Topic :: Software Development :: Libraries :: Python Modules
Requires-Python: >=3.8
Requires-Dist: socrates-ai>=1.3.0
Requires-Dist: fastapi>=0.100.0
Requires-Dist: uvicorn[standard]>=0.23.0
Requires-Dist: pydantic>=2.0.0
Requires-Dist: python-dotenv>=1.0.0
Requires-Dist: python-multipart>=0.0.5
Provides-Extra: dev
Requires-Dist: pytest>=7.0; extra == "dev"
Requires-Dist: pytest-asyncio>=0.21.0; extra == "dev"
Requires-Dist: pytest-cov>=4.0; extra == "dev"
Requires-Dist: httpx>=0.24.0; extra == "dev"
Requires-Dist: black>=23.0; extra == "dev"
Requires-Dist: ruff>=0.1.0; extra == "dev"
